example_test_oduchaine/main.py
example_test_oduchaine/s3_lister.py
example_test_oduchaine-0.1.0.dist-info/LICENSE
example_test_oduchaine-0.1.0.dist-info/METADATA
example_test_oduchaine-0.1.0.dist-info/WHEEL
example_test_oduchaine-0.1.0.dist-info/RECORD
