Metadata-Version: 2.3
Name: example-test-oduchaine
Version: 0.1.0
Summary: 
Author: Olivier Duchaine
Author-email: olivier.duchaine@gmail.com
Requires-Python: >=3.8,<4.0
Classifier: Programming Language :: Python :: 3
Classifier: Programming Language :: Python :: 3.8
Classifier: Programming Language :: Python :: 3.9
Classifier: Programming Language :: Python :: 3.10
Classifier: Programming Language :: Python :: 3.11
Classifier: Programming Language :: Python :: 3.12
Classifier: Programming Language :: Python :: 3.13
Requires-Dist: boto3 (>=1.19.7,<2.0.0)
Requires-Dist: boto3-stubs[s3] (>=1.19.7,<2.0.0)
Requires-Dist: pytz (>=2021.3,<2022.0)
Requires-Dist: tabulate (>=0.8.9,<0.9.0)
Requires-Dist: typer (>=0.4.0,<0.5.0)
